{"nodes": [{"id": "catalog_application_catalog_cache", "label": "CatalogCache", "file_type": "code", "source_file": "src/Services/Catalog/OrderSphere.Catalog.Application/Caching/CatalogCache.cs", "source_location": null, "source_url": null, "captured_at": null, "author": null, "contributor": null}, {"id": "CatalogCache", "label": "Catalog Cache", "file_type": "code", "source_file": "src/Services/Catalog/OrderSphere.Catalog.Application/Caching/CatalogCache.cs", "source_location": null, "source_url": null, "captured_at": null, "author": null, "contributor": null}], "edges": [], "hyperedges": []}